roblox_studio/__init__.py
roblox_studio/branches.py
roblox_studio/client.py
roblox_studio/cookie.py
roblox_studio/deployments.py
roblox_studio/dump.py
roblox_studio/environments.py
roblox_studio/settings.py
roblox_studio/storage.py
roblox_studio/utilities.py
roblox_studio-0.0.15.dist-info/LICENSE
roblox_studio-0.0.15.dist-info/METADATA
roblox_studio-0.0.15.dist-info/WHEEL
roblox_studio-0.0.15.dist-info/top_level.txt
roblox_studio-0.0.15.dist-info/RECORD
