Metadata-Version: 2.1
Name: roblox-studio
Version: 0.0.15
Summary: ro.py-studio is a library for interacting with Roblox installations.
Home-page: https://github.com/ro-py/ro.py-studio
Author: jmkdev
Author-email: jmk@jmksite.dev
License: UNKNOWN
Project-URL: Discord, https://discord.gg/tjRfCbDMSk
Project-URL: Issue Tracker, https://github.com/ro-py/ro.py-studio/issues
Project-URL: GitHub, https://github.com/ro-py/ro.py-studio
Project-URL: Examples, https://github.com/ro-py/ro.py-studio/tree/main/examples
Project-URL: Twitter, https://twitter.com/jmkdev
Platform: UNKNOWN
Classifier: Programming Language :: Python :: 3
Classifier: License :: OSI Approved :: MIT License
Classifier: Operating System :: OS Independent
Classifier: Framework :: AsyncIO
Classifier: Topic :: Internet :: WWW/HTTP :: Dynamic Content :: CGI Tools/Libraries
Classifier: Topic :: Software Development :: Libraries
Requires-Python: >=3.7
License-File: LICENSE
Requires-Dist: orjson (>=3.0.0)
Requires-Dist: aiohttp (>=3.8.0)
Requires-Dist: pydantic (>=1.9.0)
Requires-Dist: python-dateutil (>=2.8.0)
